{
 "problemID": 0,
 "problemNeighbors": {
  "0": "1,2",
  "1": "3,4",
  "2": "5,6",
  "3": "7,8",
  "4": "9"
 },
 "problemNumberOfRelations": 10,
 "problemRelations": [
  {
   "relationCardinality": 7558.235074915978,
   "relationName": "unknown",
   "relationPID": 0,
   "relationRID": 0
  },
  {
   "relationCardinality": 4038.0328579570037,
   "relationName": "unknown",
   "relationPID": 0,
   "relationRID": 1
  },
  {
   "relationCardinality": 1306.5111702897218,
   "relationName": "unknown",
   "relationPID": 0,
   "relationRID": 2
  },
  {
   "relationCardinality": 9859.647293402468,
   "relationName": "unknown",
   "relationPID": 0,
   "relationRID": 3
  },
  {
   "relationCardinality": 8963.417453962162,
   "relationName": "unknown",
   "relationPID": 0,
   "relationRID": 4
  },
  {
   "relationCardinality": 3220.839705208817,
   "relationName": "unknown",
   "relationPID": 0,
   "relationRID": 5
  },
  {
   "relationCardinality": 7211.477651926741,
   "relationName": "unknown",
   "relationPID": 0,
   "relationRID": 6
  },
  {
   "relationCardinality": 6445.397825093294,
   "relationName": "unknown",
   "relationPID": 0,
   "relationRID": 7
  },
  {
   "relationCardinality": 855.2050754191123,
   "relationName": "unknown",
   "relationPID": 0,
   "relationRID": 8
  },
  {
   "relationCardinality": 6695.7529769977455,
   "relationName": "unknown",
   "relationPID": 0,
   "relationRID": 9
  }
 ],
 "problemSelectivities": {
  "0,1": 0.3696928436398219,
  "0,2": 0.2368225468054852,
  "1,3": 0.5352818906344061,
  "1,4": 0.18724610140105305,
  "2,5": 0.2388407028053186,
  "2,6": 0.6280981712183633,
  "3,7": 0.1267529293726013,
  "3,8": 0.28133029380535923,
  "4,9": 0.6227283173637045
 }
}